init_provider_sqlalchemy/__init__.py
init_provider_sqlalchemy/_internal.py
init_provider_sqlalchemy-0.1.1.dist-info/METADATA
init_provider_sqlalchemy-0.1.1.dist-info/WHEEL
init_provider_sqlalchemy-0.1.1.dist-info/licenses/LICENSE
init_provider_sqlalchemy-0.1.1.dist-info/RECORD
