Metadata-Version: 2.4
Name: init-provider-sqlalchemy
Version: 0.1.1
Summary: SQLAlchemy provider for init-provider
Project-URL: Homepage, https://github.com/vduseev/init-provider-sqlalchemy
Project-URL: Documentation, https://github.com/vduseev/init-provider-sqlalchemy
Project-URL: Repository, https://github.com/vduseev/init-provider-sqlalchemy
Project-URL: Issues, https://github.com/vduseev/init-provider-sqlalchemy/issues
Author-email: vduseev <vagiz@duseev.com>
Maintainer-email: vduseev <vagiz@duseev.com>
License-Expression: Apache-2.0
License-File: LICENSE
Keywords: database,postgres,provider,service,singleton
Classifier: Development Status :: 4 - Beta
Classifier: Intended Audience :: Developers
Classifier: License :: OSI Approved :: Apache Software License
Classifier: Programming Language :: Python :: 3
Classifier: Programming Language :: Python :: 3.10
Classifier: Programming Language :: Python :: 3.11
Classifier: Programming Language :: Python :: 3.12
Classifier: Programming Language :: Python :: 3.13
Classifier: Programming Language :: Python :: 3.14
Classifier: Topic :: Software Development :: Libraries
Classifier: Topic :: Software Development :: Libraries :: Application Frameworks
Classifier: Topic :: Software Development :: Libraries :: Python Modules
Requires-Python: >=3.10
Requires-Dist: greenlet>=3.2.4
Requires-Dist: init-provider>=0.1.3
Requires-Dist: sqlalchemy>=2.0.44
